kutility/__init__.py
kutility/_nbdev.py
kutility/cli.py
kutility/core.py
kutility/selenium.py
kutility/structure.py
kutility-0.0.1.dist-info/LICENSE
kutility-0.0.1.dist-info/METADATA
kutility-0.0.1.dist-info/WHEEL
kutility-0.0.1.dist-info/entry_points.txt
kutility-0.0.1.dist-info/top_level.txt
kutility-0.0.1.dist-info/RECORD
