Metadata-Version: 2.1
Name: kutility
Version: 0.0.1
Summary: Utility package to manage recurrent task (env variable management, session authentification, pathfinder ...)
Home-page: https://github.com/Pyth314/kutility/tree/master/
Author: Pierre-Yves Thumerel
Author-email: pierre-yves.thumerel@icloud.com
License: Apache Software License 2.0
Keywords: Utility
Platform: UNKNOWN
Classifier: Development Status :: 3 - Alpha
Classifier: Intended Audience :: Developers
Classifier: License :: OSI Approved :: Apache Software License
Classifier: Natural Language :: English
Classifier: Programming Language :: Python :: 3.6
Classifier: Programming Language :: Python :: 3.7
Classifier: Programming Language :: Python :: 3.8
Requires-Python: >=3.6
Requires-Dist: pandas
Requires-Dist: pymongo
Requires-Dist: python-dotenv
Requires-Dist: selenium
Requires-Dist: setuptools
Requires-Dist: undetected-chromedriver
